maya_mongodb_package/__init__.py
maya_mongodb_package/mongodb_handler.py
maya_mongodb_package-0.1.0.dist-info/METADATA
maya_mongodb_package-0.1.0.dist-info/WHEEL
maya_mongodb_package-0.1.0.dist-info/top_level.txt
maya_mongodb_package-0.1.0.dist-info/RECORD
